cache_hook.py
crewai_cache_hook-0.1.1.dist-info/licenses/LICENSE
crewai_cache_hook-0.1.1.dist-info/METADATA
crewai_cache_hook-0.1.1.dist-info/WHEEL
crewai_cache_hook-0.1.1.dist-info/top_level.txt
crewai_cache_hook-0.1.1.dist-info/RECORD
